zhtw/__init__.py
zhtw/__main__.py
zhtw/cli.py
zhtw/config.py
zhtw/converter.py
zhtw/dictionary.py
zhtw/encoding.py
zhtw/import_terms.py
zhtw/matcher.py
zhtw/review.py
zhtw/data/terms/cn/base.json
zhtw/data/terms/cn/business.json
zhtw/data/terms/cn/chars.json
zhtw/data/terms/cn/common.json
zhtw/data/terms/cn/daily.json
zhtw/data/terms/cn/ecommerce.json
zhtw/data/terms/cn/education.json
zhtw/data/terms/cn/finance.json
zhtw/data/terms/cn/gaming.json
zhtw/data/terms/cn/geography.json
zhtw/data/terms/cn/imported.json
zhtw/data/terms/cn/it.json
zhtw/data/terms/cn/legal.json
zhtw/data/terms/cn/medical.json
zhtw/data/terms/hk/base.json
zhtw/data/terms/hk/tech.json
zhtw/data/terms/pending/.gitkeep
zhtw/data/terms/pending/import_terms.json
zhtw/llm/__init__.py
zhtw/llm/client.py
zhtw/llm/prompts.py
zhtw/llm/usage.py
zhtw-2.8.7.dist-info/METADATA
zhtw-2.8.7.dist-info/WHEEL
zhtw-2.8.7.dist-info/entry_points.txt
zhtw-2.8.7.dist-info/licenses/LICENSE
zhtw-2.8.7.dist-info/RECORD
