Metadata-Version: 2.4
Name: zhtw
Version: 2.8.7
Summary: Simplified/HK Traditional to Taiwan Traditional Chinese Converter
Project-URL: Homepage, https://github.com/rajatim/zhtw
Project-URL: Repository, https://github.com/rajatim/zhtw
Project-URL: Documentation, https://github.com/rajatim/zhtw#readme
Project-URL: Issues, https://github.com/rajatim/zhtw/issues
Project-URL: Changelog, https://github.com/rajatim/zhtw/blob/main/CHANGELOG.md
Project-URL: Blog Post (中文), https://timinsight.com/zhtw-vibe-coding-traditional-chinese-converter-zh/
Project-URL: Blog Post (English), https://timinsight.com/zhtw-vibe-coding-traditional-chinese-converter-en/
Author-email: tim Insight <rajatim@gmail.com>
License-Expression: MIT
License-File: LICENSE
Keywords: ai-tools,chinese,converter,i18n,l10n,localization,nlp,simplified,taiwan,text-processing,traditional,vibe-coding
Classifier: Development Status :: 4 - Beta
Classifier: Environment :: Console
Classifier: Intended Audience :: Developers
Classifier: License :: OSI Approved :: MIT License
Classifier: Natural Language :: Chinese (Simplified)
Classifier: Natural Language :: Chinese (Traditional)
Classifier: Operating System :: OS Independent
Classifier: Programming Language :: Python :: 3
Classifier: Programming Language :: Python :: 3.9
Classifier: Programming Language :: Python :: 3.10
Classifier: Programming Language :: Python :: 3.11
Classifier: Programming Language :: Python :: 3.12
Classifier: Programming Language :: Python :: 3.13
Classifier: Topic :: Software Development :: Internationalization
Classifier: Topic :: Software Development :: Localization
Classifier: Topic :: Text Processing :: Linguistic
Requires-Python: >=3.9
Requires-Dist: charset-normalizer>=3.0
Requires-Dist: click>=8.0
Requires-Dist: pyahocorasick>=2.0
Provides-Extra: dev
Requires-Dist: pre-commit>=3.0; extra == 'dev'
Requires-Dist: pytest-cov>=4.0; extra == 'dev'
Requires-Dist: pytest>=7.0; extra == 'dev'
Requires-Dist: ruff>=0.1; extra == 'dev'
Provides-Extra: llm
Requires-Dist: google-generativeai>=0.3; extra == 'llm'
